MANIFEST.in
README.md
setup.py
sphinxcontrib/__init__.py
sphinxcontrib/luadomain.py
sphinxcontrib_luadomain.egg-info/PKG-INFO
sphinxcontrib_luadomain.egg-info/SOURCES.txt
sphinxcontrib_luadomain.egg-info/dependency_links.txt
sphinxcontrib_luadomain.egg-info/namespace_packages.txt
sphinxcontrib_luadomain.egg-info/not-zip-safe
sphinxcontrib_luadomain.egg-info/requires.txt
sphinxcontrib_luadomain.egg-info/top_level.txt