Metadata-Version: 1.1
Name: sphinxcontrib-luadomain
Version: 1.1.0
Summary: Sphinx domain for documenting Lua code
Home-page: UNKNOWN
Author: Eliott Dumeix
Author-email: UNKNOWN
License: BSD
Platform: any
Classifier: Environment :: Console
Classifier: Environment :: Web Environment
Classifier: Intended Audience :: Developers
Classifier: License :: OSI Approved :: BSD License
Classifier: Operating System :: OS Independent
Classifier: Programming Language :: Python
Classifier: Programming Language :: Python :: 3.5
Classifier: Programming Language :: Python :: 3.6
Classifier: Topic :: Documentation
Classifier: Topic :: Utilities
